ctyunsdk_elb20220909/__init__.py
ctyunsdk_elb20220909/apis/__init__.py
ctyunsdk_elb20220909/apis/apis.py
ctyunsdk_elb20220909/apis/ctelb_associate_eip_to_load_balancer_api.py
ctyunsdk_elb20220909/apis/ctelb_async_create_certificate_api.py
ctyunsdk_elb20220909/apis/ctelb_async_create_listener_api.py
ctyunsdk_elb20220909/apis/ctelb_async_create_loadbalance_api.py
ctyunsdk_elb20220909/apis/ctelb_async_create_policy_api.py
ctyunsdk_elb20220909/apis/ctelb_async_create_target_api.py
ctyunsdk_elb20220909/apis/ctelb_check_ca_cert_api.py
ctyunsdk_elb20220909/apis/ctelb_check_server_cert_api.py
ctyunsdk_elb20220909/apis/ctelb_create_access_control_api.py
ctyunsdk_elb20220909/apis/ctelb_create_certificate_api.py
ctyunsdk_elb20220909/apis/ctelb_create_domain_cert_link_api.py
ctyunsdk_elb20220909/apis/ctelb_create_health_check_api.py
ctyunsdk_elb20220909/apis/ctelb_create_listener_api.py
ctyunsdk_elb20220909/apis/ctelb_create_load_balancer_api.py
ctyunsdk_elb20220909/apis/ctelb_create_pgelb_api.py
ctyunsdk_elb20220909/apis/ctelb_create_rule_api.py
ctyunsdk_elb20220909/apis/ctelb_create_target_api.py
ctyunsdk_elb20220909/apis/ctelb_create_target_group_api.py
ctyunsdk_elb20220909/apis/ctelb_delete_access_control_api.py
ctyunsdk_elb20220909/apis/ctelb_delete_certificate_api.py
ctyunsdk_elb20220909/apis/ctelb_delete_domain_cert_links_api.py
ctyunsdk_elb20220909/apis/ctelb_delete_health_check_api.py
ctyunsdk_elb20220909/apis/ctelb_delete_listener_api.py
ctyunsdk_elb20220909/apis/ctelb_delete_load_balancer_api.py
ctyunsdk_elb20220909/apis/ctelb_delete_rule_api.py
ctyunsdk_elb20220909/apis/ctelb_delete_target_api.py
ctyunsdk_elb20220909/apis/ctelb_delete_target_group_api.py
ctyunsdk_elb20220909/apis/ctelb_disable_elb_ipv6_api.py
ctyunsdk_elb20220909/apis/ctelb_disassociate_eip_from_load_balancer_api.py
ctyunsdk_elb20220909/apis/ctelb_elb_bind_labels_api.py
ctyunsdk_elb20220909/apis/ctelb_elb_create_access_log_api.py
ctyunsdk_elb20220909/apis/ctelb_elb_delete_access_log_api.py
ctyunsdk_elb20220909-1.0.0.dist-info/LICENSE.txt
ctyunsdk_elb20220909-1.0.0.dist-info/METADATA
ctyunsdk_elb20220909-1.0.0.dist-info/WHEEL
ctyunsdk_elb20220909-1.0.0.dist-info/top_level.txt
ctyunsdk_elb20220909-1.0.0.dist-info/RECORD
