Metadata-Version: 2.1
Name: ctyunsdk-elb20220909
Version: 1.0.0
Summary: CTYun ELB (2022-09-09) SDK Library for Python
Home-page: https://github.com/ctyunsdk/ctyun-python-sdk.git
Author: Ctyun Cloud SDK
Author-email: ctyunsdk@chinatelecom.cn
License: UNKNOWN
Keywords: ctyunsdk,elb20220909
Platform: any
Classifier: Development Status :: 4 - Beta
Classifier: Intended Audience :: Developers
Classifier: License :: OSI Approved :: Apache Software License
Classifier: Operating System :: OS Independent
Classifier: Programming Language :: Python :: 3
Classifier: Programming Language :: Python :: 3.9
Classifier: Programming Language :: Python :: 3.10
Requires-Python: >=3.9
Requires-Dist: setuptools
Requires-Dist: requests>=2.25.0
